ktkkt_downloader/__init__.py
ktkkt_downloader/ktkkt_downloader.py
ktkkt_downloader/downloader/__init__.py
ktkkt_downloader/downloader/downloader.py
ktkkt_downloader/logger/__init__.py
ktkkt_downloader/logger/logger.py
ktkkt_downloader/object/__init__.py
ktkkt_downloader/object/episode.py
ktkkt_downloader/scraper/__init__.py
ktkkt_downloader/scraper/ktkkt_strategy.py
ktkkt_downloader/scraper/scraper.py
ktkkt_downloader/scraper/strategy.py
tests/__init__.py
tests/test_logger.py
tests/test_scraper.py
ktkkt_downloader-1.0.1.dist-info/LICENSE.md
ktkkt_downloader-1.0.1.dist-info/METADATA
ktkkt_downloader-1.0.1.dist-info/WHEEL
ktkkt_downloader-1.0.1.dist-info/top_level.txt
ktkkt_downloader-1.0.1.dist-info/RECORD
