Metadata-Version: 2.1
Name: ktkkt-downloader
Version: 1.0.1
Summary: downloader for videos on ktkkt.cc
Home-page: https://github.com/rkwyu/ktkkt-downloader
Author: rkwyu
Author-email: rkwyu <ray.yukawai@gmail.com>
Classifier: Programming Language :: Python :: 3
Classifier: License :: OSI Approved :: Apache Software License
Classifier: Operating System :: OS Independent
Requires-Python: >=3.8
License-File: LICENSE.md
Requires-Dist: beautifulsoup4 (>=4.10.0)
Requires-Dist: ffmpeg-python (>=0.2.0)
Requires-Dist: pathvalidate (>=2.4.1)
Requires-Dist: regex (>=2021.8.28)
Requires-Dist: requests (>=2.26.0)
